interactions/ext/cooldowns/__init__.py
interactions/ext/cooldowns/cooldowns.py
interactions_cooldowns-1.0.5.dist-info/LICENSE
interactions_cooldowns-1.0.5.dist-info/METADATA
interactions_cooldowns-1.0.5.dist-info/WHEEL
interactions_cooldowns-1.0.5.dist-info/top_level.txt
interactions_cooldowns-1.0.5.dist-info/RECORD
