Metadata-Version: 2.1
Name: interactions-cooldowns
Version: 1.0.5
Summary: description
Home-page: https://github.com/dontbanmeplz/interactions-cooldowns
Author: dontbanmeplz
Author-email: example@email.domain
License: MIT
Platform: UNKNOWN
Classifier: Programming Language :: Python :: 3
Classifier: Development Status :: 4 - Beta
Classifier: License :: OSI Approved :: MIT License
Classifier: Operating System :: OS Independent
License-File: LICENSE
Requires-Dist: discord-py-interactions (>=4.0.2)
